LICENSE
MANIFEST.in
README.rst
setup.py
upload.bat
vdirect_client/__init__.py
vdirect_client/rest_client.py
vdirect_client.egg-info/PKG-INFO
vdirect_client.egg-info/SOURCES.txt
vdirect_client.egg-info/dependency_links.txt
vdirect_client.egg-info/not-zip-safe
vdirect_client.egg-info/top_level.txt