Metadata-Version: 1.1
Name: vdirect-client
Version: 4.4.0-1
Summary: Radware vDirect server python REST client
Home-page: https://pypi.python.org/pypi/vdirect_client
Author: Avishay Balderman
Author-email: avishayb@radware.com
License: ASL 2.0
Keywords: radware vdirect python REST client
Platform: UNKNOWN
Classifier: Environment :: Other Environment
Classifier: Intended Audience :: Developers
Classifier: Intended Audience :: System Administrators
Classifier: License :: OSI Approved :: Apache Software License
Classifier: Operating System :: POSIX :: Linux
Classifier: Programming Language :: Python
